.DS_Store
nii2png/__init__.py
nii2png/nii2png.py
nii2png-0.3.0.data/scripts/nii2png
nii2png-0.3.0.dist-info/LICENSE
nii2png-0.3.0.dist-info/METADATA
nii2png-0.3.0.dist-info/WHEEL
nii2png-0.3.0.dist-info/top_level.txt
nii2png-0.3.0.dist-info/RECORD
