Metadata-Version: 2.1
Name: nii2png
Version: 0.3.0
Summary: A lightweight neuroimaging .nii to .png converter
Home-page: https://github.com/alexlaurence/NIfTI-Image-Converter
Author: Alexander Laurence
Author-email: alexander.adamlaurence@gmail.com
License: MIT
Platform: UNKNOWN
Classifier: Programming Language :: Python :: 3
Classifier: License :: OSI Approved :: MIT License
Classifier: Operating System :: OS Independent
Requires-Dist: scipy
Requires-Dist: shutil
Requires-Dist: nibabel
Requires-Dist: numpy
